gortztools/__init__.py
gortz_tools-0.5.dist-info/LICENSE
gortz_tools-0.5.dist-info/METADATA
gortz_tools-0.5.dist-info/WHEEL
gortz_tools-0.5.dist-info/top_level.txt
gortz_tools-0.5.dist-info/RECORD
