Metadata-Version: 2.1
Name: gortz-tools
Version: 0.5
Summary: Collections of tools to gathering data to mysql database
Home-page: https://github.com/SweGortz/gortz-tools
Author: Adrian Gortzak
Author-email: addegor95@gmail.com
License: MIT
Platform: UNKNOWN
